CHANGES.rst
MANIFEST.in
README.rst
setup.py
django_deferred_polymorph/__init__.py
django_deferred_polymorph/apps.py
django_deferred_polymorph/compat.py
django_deferred_polymorph/deferred.py
django_deferred_polymorph/manager.py
django_deferred_polymorph/models.py
django_deferred_polymorph/patch_relations.py
django_deferred_polymorph/query.py
django_deferred_polymorph/views.py
django_deferred_polymorph.egg-info/PKG-INFO
django_deferred_polymorph.egg-info/SOURCES.txt
django_deferred_polymorph.egg-info/dependency_links.txt
django_deferred_polymorph.egg-info/requires.txt
django_deferred_polymorph.egg-info/top_level.txt
tests/__init__.py
tests/models.py
tests/settings.py
tests/test_manager.py
tests/test_modelapi.py