Metadata-Version: 1.1
Name: django-deferred-polymorph
Version: 0.4.0
Summary: Polymorphic models based on django deferred models
Home-page: https://github.com/ddanier/django_deferred_polymorph
Author: David Danier
Author-email: david.danier@team23.de
License: UNKNOWN
Platform: UNKNOWN
Classifier: Development Status :: 4 - Beta
Classifier: Environment :: Web Environment
Classifier: Framework :: Django
Classifier: Intended Audience :: Developers
Classifier: License :: OSI Approved :: BSD License
Classifier: Operating System :: OS Independent
Classifier: Programming Language :: Python
Classifier: Topic :: Utilities
